{
    "configurations": [
        {
            "name": "Mac",
            "includePath": [
                "${workspaceFolder}/**",
                "/Library/Developer/CommandLineTools/usr/include/"
            ],
            "defines": [],
            "macFrameworkPath": [
                "/Library/Developer/CommandLineTools/SDKs/MacOSX.sdk/System/Library/Frameworks"
            ],
            "compilerPath": "/opt/homebrew/bin/gcc",
            "intelliSenseMode": "macos-clang-arm64"
        }
    ],
    "version": 4
}